odoo/addons/partner_delivery_schedule/README.rst
odoo/addons/partner_delivery_schedule/__init__.py
odoo/addons/partner_delivery_schedule/__manifest__.py
odoo/addons/partner_delivery_schedule/i18n/es.po
odoo/addons/partner_delivery_schedule/i18n/partner_delivery_schedule.pot
odoo/addons/partner_delivery_schedule/models/__init__.py
odoo/addons/partner_delivery_schedule/models/partner_delivery_schedule.py
odoo/addons/partner_delivery_schedule/models/res_partner.py
odoo/addons/partner_delivery_schedule/readme/CONTRIBUTORS.rst
odoo/addons/partner_delivery_schedule/readme/DESCRIPTION.rst
odoo/addons/partner_delivery_schedule/readme/USAGE.rst
odoo/addons/partner_delivery_schedule/security/ir.model.access.csv
odoo/addons/partner_delivery_schedule/static/description/icon.png
odoo/addons/partner_delivery_schedule/static/description/index.html
odoo/addons/partner_delivery_schedule/tests/__init__.py
odoo/addons/partner_delivery_schedule/tests/test_partner_delivery_schedule.py
odoo/addons/partner_delivery_schedule/views/partner_delivery_schedule_view.xml
odoo/addons/partner_delivery_schedule/views/report_shipping.xml
odoo/addons/partner_delivery_schedule/views/res_partner_view.xml
odoo11_addon_partner_delivery_schedule-11.0.1.0.1.dist-info/METADATA
odoo11_addon_partner_delivery_schedule-11.0.1.0.1.dist-info/RECORD
odoo11_addon_partner_delivery_schedule-11.0.1.0.1.dist-info/WHEEL
odoo11_addon_partner_delivery_schedule-11.0.1.0.1.dist-info/top_level.txt
